sqlitemap/__init__.py
sqlitemap/constants.py
sqlitemap/json.py
sqlitemap-0.2.0.dist-info/LICENSE
sqlitemap-0.2.0.dist-info/METADATA
sqlitemap-0.2.0.dist-info/WHEEL
sqlitemap-0.2.0.dist-info/top_level.txt
sqlitemap-0.2.0.dist-info/zip-safe
sqlitemap-0.2.0.dist-info/RECORD
