Metadata-Version: 2.1
Name: sqlitemap
Version: 0.2.0
Summary: Dictionary interface to an SQLite database
Home-page: https://github.com/eigenein/sqlitemap
Author: Pavel Perestoronin
Author-email: eigenein@gmail.com
License: UNKNOWN
Platform: UNKNOWN
Classifier: Development Status :: 4 - Beta
Classifier: Intended Audience :: Developers
Classifier: Operating System :: OS Independent
Classifier: Topic :: Software Development :: Libraries
Classifier: Topic :: Software Development :: Libraries :: Python Modules
Classifier: Programming Language :: Python :: 3.6
Classifier: Programming Language :: Python :: 3.7
Classifier: License :: OSI Approved :: MIT License
Provides-Extra: dev
Requires-Dist: flake8 ; extra == 'dev'
Requires-Dist: isort ; extra == 'dev'
Requires-Dist: pytest ; extra == 'dev'
Requires-Dist: pytest-cov ; extra == 'dev'
Requires-Dist: coveralls ; extra == 'dev'
Requires-Dist: ujson ; extra == 'dev'
Requires-Dist: orjson ; extra == 'dev'
Requires-Dist: twine ; extra == 'dev'
Requires-Dist: mypy ; extra == 'dev'
Provides-Extra: orjson
Requires-Dist: orjson ; extra == 'orjson'
Provides-Extra: ujson
Requires-Dist: ujson ; extra == 'ujson'
